[
  {
    "@id": "https://nakamura196.github.io/lda/data/json/yanesen_06_025.json",
    "http://purl.org/dc/terms/creator": [
      {
        "@value": "加宮貴一"
      }
    ],
    "http://purl.org/dc/terms/identifier": [
      {
        "@value": "yanesen/06/025"
      }
    ],
    "http://purl.org/dc/terms/relation": [
      {
        "@id": "https://nakamura196.github.io/uv/?manifest=https://nakamura196.github.io/lda/data/manifest/yanesen_06_025.json"
      }
    ],
    "http://purl.org/dc/terms/title": [
      {
        "@value": "谷根千の風景　崖の四季"
      }
    ],
    "http://xmlns.com/foaf/0.1/thumbnail": [
      {
        "@id": "https://nakamura196.github.io/lda/data/images/yanesen/yanesen-06/yanesen-06-010.jpg"
      }
    ]
  }
]